Workbook

Sheet Данные
A1: Цель: обосновать коэффициенты значимости (удельные веса)
A2: доходного, затратного, сравнительного подходов к оценке стоимости бизнеса для определения итоговой величины стоимости.
A4: Критерии
A5: 1 | B5: возможность отразить действительные намерения продавца;
A6: 2 | B6: тип, качество, обширность данных, на основе которых проводится анализ;
A7: 3 | B7: способность параметров используемых методов учитывать конъюнктурные колебания;
A8: 4 | B8: способность учитывать специфические особенности объекта, влияющие на его стоимость (местонахождение, размер, потенциальная доходность).
A10: Размер матрицы критериев | D10: 4
A11: Случайная согласованность | D11: 0.9
A13: Альтернативы
A14: З | B14: затратный подход к оценке
A15: С | B15: сравнительный подход к оценке
A16: Д | B16: доходный подход к оценке
A18: Размер матрицы альтернатив | D18: 3
A19: Случайная согласованнсть | D19: 0.58

Sheet Критерии
B1: К1 | C1: К2 | D1: К3 | E1: К4 | F1: Средние геом. | G1: НВП
A2: К1 | B2: 1 | C2: =1/2 -> 0.5 | D2: 3 | E2: 2 | F2: =POWER(PRODUCT(B2:E2), 1/4) -> 1.316074 | G2: =F2/$F$6 -> 0.30786405
A3: К2 | B3: =1/C2 -> 2 | C3: 1 | D3: 3 | E3: 1 | F3: =POWER(PRODUCT(B3:E3), 1/4) -> 1.5650846 | G3: =F3/$F$6 -> 0.36611412
A4: К3 | B4: =1/D2 -> 0.33333333 | C4: =1/D3 -> 0.33333333 | D4: 1 | E4: 2 | F4: =POWER(PRODUCT(B4:E4), 1/4) -> 0.68658905 | G4: =F4/$F$6 -> 0.16061109
A5: К4 | B5: =1/E2 -> 0.5 | C5: =1/E3 -> 1 | D5: =1/E4 -> 0.5 | E5: 1 | F5: =POWER(PRODUCT(B5:E5), 1/4) -> 0.70710678 | G5: =F5/$F$6 -> 0.16541073
A6: Итого | B6: =SUM(B2:B5) -> 3.8333333 | C6: =SUM(C2:C5) -> 2.8333333 | D6: =SUM(D2:D5) -> 7.5 | E6: =SUM(E2:E5) -> 6 | F6: =SUM(F2:F5) -> 4.2748544 | G6: =SUM(G2:G5) -> 1
A7: L_max | B7: =B6*G2+C6*G3+D6*G4+E6*G5 -> 4.4145165
A8: ИС | B8: =(B7-Данные!D10)/(Данные!D10 - 1) -> 0.13817216
A9: ОС | B9: =B8/Данные!D11 -> 0.15352462

Sheet K1
B1: З | C1: С | D1: Д | E1: Средние геом. | F1: НВП
A2: З | B2: 1 | C2: =1/2 -> 0.5 | D2: =1/3 -> 0.33333333 | E2: =POWER(PRODUCT(B2:D2), 1/3) -> 0.55032121 | F2: =E2/$E$5 -> 0.16342412
A3: С | B3: =1/C2 -> 2 | C3: 1 | D3: =1/2 -> 0.5 | E3: =POWER(PRODUCT(B3:D3), 1/3) -> 1 | F3: =E3/$E$5 -> 0.29696133
A4: Д | B4: =1/D2 -> 3 | C4: =1/D3 -> 2 | D4: 1 | E4: =POWER(PRODUCT(B4:D4), 1/3) -> 1.8171206 | F4: =E4/$E$5 -> 0.53961455
A5: Итого | B5: =SUM(B2:B4) -> 6 | C5: =SUM(C2:C4) -> 3.5 | D5: =SUM(D2:D4) -> 1.8333333 | E5: =SUM(E2:E4) -> 3.3674418 | F5: =SUM(F2:F4) -> 1
A6: L_max А | B6: =B5*F2+C5*F3+D5*F4 -> 3.0092027
A7: ИС А | B7: =(B6-Данные!D18)/(Данные!D18 - 1) -> 0.0046013564
A8: ОС А | B8: =B7/Данные!D19 -> 0.007933373

Sheet K2
B1: З | C1: С | D1: Д | E1: Средние геом. | F1: НВП
A2: З | B2: 1 | C2: 3 | D2: 5 | E2: =POWER(PRODUCT(B2:D2), 1/3) -> 2.4662121 | F2: =E2/$E$5 -> 0.63698557
A3: С | B3: =1/C2 -> 0.33333333 | C3: 1 | D3: 3 | E3: =POWER(PRODUCT(B3:D3), 1/3) -> 1 | F3: =E3/$E$5 -> 0.25828499
A4: Д | B4: =1/D2 -> 0.2 | C4: =1/D3 -> 0.33333333 | D4: 1 | E4: =POWER(PRODUCT(B4:D4), 1/3) -> 0.40548013 | F4: =E4/$E$5 -> 0.10472943
A5: Итого | B5: =SUM(B2:B4) -> 1.5333333 | C5: =SUM(C2:C4) -> 4.3333333 | D5: =SUM(D2:D4) -> 9 | E5: =SUM(E2:E4) -> 3.8716922 | F5: =SUM(F2:F4) -> 1
A6: L_max Б | B6: =B5*F2+C5*F3+D5*F4 -> 3.0385111
A7: ИС Б | B7: =(B6-Данные!D18)/(Данные!D18 - 1) -> 0.019255545
A8: ОС Б | B8: =B7/Данные!D19 -> 0.033199216

Sheet K3
B1: З | C1: С | D1: Д | E1: Средние геом. | F1: НВП
A2: З | B2: 1 | C2: =1/2 -> 0.5 | D2: =1/2 -> 0.5 | E2: =POWER(PRODUCT(B2:D2), 1/3) -> 0.62996052 | F2: =E2/$E$5 -> 0.19580035
A3: С | B3: =1/C2 -> 2 | C3: 1 | D3: =1/2 -> 0.5 | E3: =POWER(PRODUCT(B3:D3), 1/3) -> 1 | F3: =E3/$E$5 -> 0.31081368
A4: Д | B4: =1/D2 -> 2 | C4: =1/D3 -> 2 | D4: 1 | E4: =POWER(PRODUCT(B4:D4), 1/3) -> 1.5874011 | F4: =E4/$E$5 -> 0.49338597
A5: Итого | B5: =SUM(B2:B4) -> 5 | C5: =SUM(C2:C4) -> 3.5 | D5: =SUM(D2:D4) -> 2 | E5: =SUM(E2:E4) -> 3.2173616 | F5: =SUM(F2:F4) -> 1
A6: L_max В | B6: =B5*F2+C5*F3+D5*F4 -> 3.0536216
A7: ИС В | B7: =(B6-Данные!D18)/(Данные!D18 - 1) -> 0.026810788
A8: ОС В | B8: =B7/Данные!D19 -> 0.046225496

Sheet K4
B1: З | C1: С | D1: Д | E1: Средние геом. | F1: НВП
A2: З | B2: 1 | C2: 2 | D2: 3 | E2: =POWER(PRODUCT(B2:D2), 1/3) -> 1.8171206 | F2: =E2/$E$5 -> 0.54721643
A3: С | B3: =1/C2 -> 0.5 | C3: 1 | D3: =1/2 -> 0.5 | E3: =POWER(PRODUCT(B3:D3), 1/3) -> 0.62996052 | F3: =E3/$E$5 -> 0.18970934
A4: Д | B4: =1/D2 -> 0.33333333 | C4: =1/D3 -> 2 | D4: 1 | E4: =POWER(PRODUCT(B4:D4), 1/3) -> 0.87358046 | F4: =E4/$E$5 -> 0.26307422
A5: Итого | B5: =SUM(B2:B4) -> 1.8333333 | C5: =SUM(C2:C4) -> 5 | D5: =SUM(D2:D4) -> 4.5 | E5: =SUM(E2:E4) -> 3.3206616 | F5: =SUM(F2:F4) -> 1
A6: L_max Г | B6: =B5*F2+C5*F3+D5*F4 -> 3.1356108
A7: ИС Г | B7: =(B6-Данные!D18)/(Данные!D18 - 1) -> 0.067805422
A8: ОС Г | B8: =B7/Данные!D19 -> 0.1169059

Sheet Итог
B1: К1 | C1: К2 | D1: К3 | E1: К4 | F1: Итоговая оценка коэф.
B2: {=TRANSPOSE(Критерии!G2:G5)} -> 0.30786405 | C2: 0.36611412 | D2: 0.16061109 | E2: 0.16541073
A3: З | B3: {='K1'!F2:F4} -> 0.16342412 | C3: {='K2'!F2:F4} -> 0.63698557 | D3: {='K3'!F2:F4} -> 0.19580035 | E3: {='K4'!F2:F4} -> 0.54721643 | F3: =B$2*B3+C$2*C3+D$2*D3+E$2*E3 -> 0.405485 | G3: Наиболее предпочтительный
A4: С | B4: 0.29696133 | C4: 0.25828499 | D4: 0.31081368 | E4: 0.18970934 | F4: =B$2*B4+C$2*C4+D$2*D4+E$2*E4 -> 0.26728559 | G4: Наименее предпочтительный
A5: Д | B5: 0.53961455 | C5: 0.10472943 | D5: 0.49338597 | E5: 0.26307422 | F5: =B$2*B5+C$2*C5+D$2*D5+E$2*E5 -> 0.32722941
A6: ИС | B6: ='K1'!B7 -> 0.0046013564 | C6: ='K2'!B7 -> 0.019255545 | D6: ='K3'!B7 -> 0.026810788 | E6: ='K4'!B7 -> 0.067805422
A7: ОИС | B7: =B2*B6+C2*C6+D2*D6+E2*E6 -> 0.023988174
A8: ООС | B8: =B7/Данные!D19 -> 0.04135892

Sheet |

Sheet 2Данные
A1: Цель: обосновать коэффициенты значимости (удельные веса)
A2: доходного, затратного, сравнительного подходов к оценке стоимости бизнеса для определения итоговой величины стоимости.
A4: Критерии
A5: 1 | B5: Защищенность. Способность предотвращать несанкционированный доступ. Критично для баз данных, хранящих чувствительную информацию.
A6: 2 | B6: Устойчивость к ошибке. Способность поддерживать работу при сбоях (отказоустойчивость, механизмы репликации).
A7: 3 | B7: Характер изменения во времени. Времена отклика и скорость обработки запросов (производительность).
A8: 4 | B8: Адаптируемость. Удобство адаптации к различным условиям эксплуатации (поддержка разных ОС, легкость развертывания).
A9: 5 | B9: Стоимость. Цена лицензирования и совокупная стоимость владения (TCO).
A10: 6 | B10: Популярность и поддержка сообщества. Наличие специалистов на рынке, документации и готовых решений (StackOverflow, форумы)
A12: Размер матрицы критериев | D12: 6
A13: Случайная согласованность | D13: 1.24
A15: Альтернативы
A16: My | B16: MySQL
A17: Postgres | B17: PostgreSQL
A18: MS | B18: MS SQL Server
A20: Размер матрицы альтернатив | D20: 3
A21: Случайная согласованнсть | D21: 0.58

Sheet 2Опис
A1: Характеристика | B1: MySQL | C1: PostgreSQL | D1: MS SQL Server
A2: К1. Защищенность | B2: Хорошая. Есть управление правами, шифрование. Исторически «из коробки» была менее безопасна, чем конкуренты. | C2: Очень высокая. Развитая система ролей (RLS), мощные механизмы аутентификации. | D2: Эталонная. Тесная интеграция с Windows Security/AD, прозрачное шифрование данных, маскирование. Считается одной из самых безопасных.
A3: К2. Устойчивость (Надежность) | B3: Хорошая. Репликация (Master-Slave) работает надежно, но сложна в настройке для строгой консистентности. | C3: Отличная. Write Ahead Log (WAL), синхронная репликация, проверенная надежность данных (ACID). | D3: Отличная. Технология AlwaysOn Availability Groups обеспечивает высочайшую доступность и автоматическое переключение.
A4: К3. Производительность (Время) | B4: Высокая скорость на простых операциях чтения. Может уступать в сложных аналитических запросах. | C4: Сбалансированная. Отлично справляется со сложными JOIN-запросами и большими объемами данных. | D4: Высочайшая. Оптимизатор запросов считается одним из лучших в мире. Отличная работа с большими нагрузками.
A5: К4. Адаптируемость (ОС) | B5: Работает везде (Linux, Windows, macOS, BSD). «Родная» среда — Linux. | C5: Работает везде. Отличная переносимость. | D5: Только Windows. Экосистема жестко привязана к Windows.
A6: К5. Стоимость | B6: Бесплатно (GPL), есть платные Enterprise версии от Oracle, но Community версия полнофункциональна. | C6: Бесплатно (BSD-подобная лицензия). Полностью открыта. | D6: Лицензирование Enterprise-версии стоит десятки тысяч долларов.
A7: К6. Сообщество | B7: Огромное. Стандарт де-факто для веб-разработки (LAMP). Много хостингов. | C7: Очень большое и активное. Быстрорастущее сообщество разработчиков. | D7: Большое, но профессиональное/корпоративное. Поддержка платная от Microsoft — качественная, но дорогая.

Sheet 2Критерии
B1: К1 | C1: К2 | D1: К3 | E1: К4 | F1: К5 | G1: К6 | H1: Средние геом. | I1: НВП
A2: К1 | B2: 1 | C2: =1/2 -> 0.5 | D2: 1 | E2: 3 | F2: =1/3 -> 0.33333333 | G2: 2 | H2: =POWER(PRODUCT(B2:G2), 1/6) -> 1 | I2: =H2/$H$8 -> 0.13643914
A3: К2 | B3: =1/C2 -> 2 | C3: 1 | D3: 2 | E3: 4 | F3: =1/2 -> 0.5 | G3: 3 | H3: =POWER(PRODUCT(B3:G3), 1/6) -> 1.6983813 | I3: =H3/$H$8 -> 0.23172569
A4: К3 | B4: =1/D2 -> 1 | C4: =1/D3 -> 0.5 | D4: 1 | E4: 3 | F4: =1/3 -> 0.33333333 | G4: 2 | H4: =POWER(PRODUCT(B4:G4), 1/6) -> 1 | I4: =H4/$H$8 -> 0.13643914
A5: К4 | B5: =1/E2 -> 0.33333333 | C5: =1/E3 -> 0.25 | D5: =1/E4 -> 0.33333333 | E5: 1 | F5: =1/5 -> 0.2 | G5: =1/2 -> 0.5 | H5: =POWER(PRODUCT(B5:G5), 1/6) -> 0.37492947 | I5: =H5/$H$8 -> 0.051155056
A6: К5 | B6: =1/F2 -> 3 | C6: =1/F3 -> 2 | D6: =1/F4 -> 3 | E6: =1/F5 -> 5 | F6: 1 | G6: 4 | H6: =POWER(PRODUCT(B6:G6), 1/6) -> 2.6671683 | I6: =H6/$H$8 -> 0.36390615
A7: К6 | B7: =1/G2 -> 0.5 | C7: =1/G3 -> 0.33333333 | D7: =1/G4 -> 0.5 | E7: =1/G5 -> 2 | F7: =1/G6 -> 0.25 | G7: 1 | H7: =POWER(PRODUCT(B7:G7), 1/6) -> 0.58879592 | I7: =H7/$H$8 -> 0.080334811
A8: Итого | B8: =SUM(B2:B7) -> 7.8333333 | C8: =SUM(C2:C7) -> 4.5833333 | D8: =SUM(D2:D7) -> 7.8333333 | E8: =SUM(E2:E7) -> 18 | F8: =SUM(F2:F7) -> 2.6166667 | G8: =SUM(G2:G7) -> 12.5 | H8: =SUM(H2:H7) -> 7.329275 | I8: =SUM(I2:I7) -> 1
A9: L_max | B9: =B8*I2+C8*I3+D8*I4+E8*I5+F8*I6+G8*I7 -> 6.0768199
A10: ИС | B10: =(B9-'2Данные'!D12)/('2Данные'!D12 - 1) -> 0.015363984
A11: ОС | B11: =B10/'2Данные'!D13 -> 0.012390309

Sheet 2K1
B1: My | C1: Postgres | D1: MS | E1: Средние геом. | F1: НВП
A2: My | B2: 1 | C2: =1/2 -> 0.5 | D2: =1/3 -> 0.33333333 | E2: =POWER(PRODUCT(B2:D2), 1/3) -> 0.55032121 | F2: =E2/$E$5 -> 0.16342412
A3: Postgres | B3: =1/C2 -> 2 | C3: 1 | D3: =1/2 -> 0.5 | E3: =POWER(PRODUCT(B3:D3), 1/3) -> 1 | F3: =E3/$E$5 -> 0.29696133
A4: MS | B4: =1/D2 -> 3 | C4: =1/D3 -> 2 | D4: 1 | E4: =POWER(PRODUCT(B4:D4), 1/3) -> 1.8171206 | F4: =E4/$E$5 -> 0.53961455
A5: Итого | B5: =SUM(B2:B4) -> 6 | C5: =SUM(C2:C4) -> 3.5 | D5: =SUM(D2:D4) -> 1.8333333 | E5: =SUM(E2:E4) -> 3.3674418 | F5: =SUM(F2:F4) -> 1
A6: L_max | B6: =B5*F2+C5*F3+D5*F4 -> 3.0092027
A7: ИС | B7: =(B6-'2Данные'!D20)/('2Данные'!D20 - 1) -> 0.0046013564
A8: ОС | B8: =B7/'2Данные'!D21 -> 0.007933373

Sheet 2K2
B1: My | C1: Postgres | D1: MS | E1: Средние геом. | F1: НВП
A2: My | B2: 1 | C2: =1/3 -> 0.33333333 | D2: =1/3 -> 0.33333333 | E2: =POWER(PRODUCT(B2:D2), 1/3) -> 0.48074986 | F2: =E2/$E$5 -> 0.14285714
A3: Postgres | B3: =1/C2 -> 3 | C3: 1 | D3: =1 -> 1 | E3: =POWER(PRODUCT(B3:D3), 1/3) -> 1.4422496 | F3: =E3/$E$5 -> 0.42857143
A4: MS | B4: =1/D2 -> 3 | C4: =1/D3 -> 1 | D4: 1 | E4: =POWER(PRODUCT(B4:D4), 1/3) -> 1.4422496 | F4: =E4/$E$5 -> 0.42857143
A5: Итого | B5: =SUM(B2:B4) -> 7 | C5: =SUM(C2:C4) -> 2.3333333 | D5: =SUM(D2:D4) -> 2.3333333 | E5: =SUM(E2:E4) -> 3.365249 | F5: =SUM(F2:F4) -> 1
A6: L_max | B6: =B5*F2+C5*F3+D5*F4 -> 3
A7: ИС | B7: =(B6-'2Данные'!D20)/('2Данные'!D20 - 1) -> 0
A8: ОС | B8: =B7/'2Данные'!D21 -> 0

Sheet 2K3
B1: My | C1: Postgres | D1: MS | E1: Средние геом. | F1: НВП
A2: My | B2: 1 | C2: 1 | D2: =1/2 -> 0.5 | E2: =POWER(PRODUCT(B2:D2), 1/3) -> 0.79370053 | F2: =E2/$E$5 -> 0.25
A3: Postgres | B3: =1/C2 -> 1 | C3: 1 | D3: =1/2 -> 0.5 | E3: =POWER(PRODUCT(B3:D3), 1/3) -> 0.79370053 | F3: =E3/$E$5 -> 0.25
A4: MS | B4: =1/D2 -> 2 | C4: =1/D3 -> 2 | D4: 1 | E4: =POWER(PRODUCT(B4:D4), 1/3) -> 1.5874011 | F4: =E4/$E$5 -> 0.5
A5: Итого | B5: =SUM(B2:B4) -> 4 | C5: =SUM(C2:C4) -> 4 | D5: =SUM(D2:D4) -> 2 | E5: =SUM(E2:E4) -> 3.1748021 | F5: =SUM(F2:F4) -> 1
A6: L_max | B6: =B5*F2+C5*F3+D5*F4 -> 3
A7: ИС | B7: =(B6-'2Данные'!D20)/('2Данные'!D20 - 1) -> 2.220446e-16
A8: ОС | B8: =B7/'2Данные'!D21 -> 3.8283553e-16

Sheet 2K4
B1: My | C1: Postgres | D1: MS | E1: Средние геом. | F1: НВП
A2: My | B2: 1 | C2: 1 | D2: 5 | E2: =POWER(PRODUCT(B2:D2), 1/3) -> 1.7099759 | F2: =E2/$E$5 -> 0.45454545
A3: Postgres | B3: =1/C2 -> 1 | C3: 1 | D3: 5 | E3: =POWER(PRODUCT(B3:D3), 1/3) -> 1.7099759 | F3: =E3/$E$5 -> 0.45454545
A4: MS | B4: =1/D2 -> 0.2 | C4: =1/D3 -> 0.2 | D4: 1 | E4: =POWER(PRODUCT(B4:D4), 1/3) -> 0.34199519 | F4: =E4/$E$5 -> 0.090909091
A5: Итого | B5: =SUM(B2:B4) -> 2.2 | C5: =SUM(C2:C4) -> 2.2 | D5: =SUM(D2:D4) -> 11 | E5: =SUM(E2:E4) -> 3.7619471 | F5: =SUM(F2:F4) -> 1
A6: L_max | B6: =B5*F2+C5*F3+D5*F4 -> 3
A7: ИС | B7: =(B6-'2Данные'!D20)/('2Данные'!D20 - 1) -> 0
A8: ОС | B8: =B7/'2Данные'!D21 -> 0

Sheet 2K5
B1: My | C1: Postgres | D1: MS | E1: Средние геом. | F1: НВП
A2: My | B2: 1 | C2: 1 | D2: 9 | E2: =POWER(PRODUCT(B2:D2), 1/3) -> 2.0800838 | F2: =E2/$E$5 -> 0.47368421
A3: Postgres | B3: =1/C2 -> 1 | C3: 1 | D3: 9 | E3: =POWER(PRODUCT(B3:D3), 1/3) -> 2.0800838 | F3: =E3/$E$5 -> 0.47368421
A4: MS | B4: =1/D2 -> 0.11111111 | C4: =1/D3 -> 0.11111111 | D4: 1 | E4: =POWER(PRODUCT(B4:D4), 1/3) -> 0.23112042 | F4: =E4/$E$5 -> 0.052631579
A5: Итого | B5: =SUM(B2:B4) -> 2.1111111 | C5: =SUM(C2:C4) -> 2.1111111 | D5: =SUM(D2:D4) -> 19 | E5: =SUM(E2:E4) -> 4.3912881 | F5: =SUM(F2:F4) -> 1
A6: L_max | B6: =B5*F2+C5*F3+D5*F4 -> 3
A7: ИС | B7: =(B6-'2Данные'!D20)/('2Данные'!D20 - 1) -> 0
A8: ОС | B8: =B7/'2Данные'!D21 -> 0

Sheet 2K6
B1: My | C1: Postgres | D1: MS | E1: Средние геом. | F1: НВП
A2: My | B2: 1 | C2: 2 | D2: 3 | E2: =POWER(PRODUCT(B2:D2), 1/3) -> 1.8171206 | F2: =E2/$E$5 -> 0.53961455
A3: Postgres | B3: =1/C2 -> 0.5 | C3: 1 | D3: 2 | E3: =POWER(PRODUCT(B3:D3), 1/3) -> 1 | F3: =E3/$E$5 -> 0.29696133
A4: MS | B4: =1/D2 -> 0.33333333 | C4: =1/D3 -> 0.5 | D4: 1 | E4: =POWER(PRODUCT(B4:D4), 1/3) -> 0.55032121 | F4: =E4/$E$5 -> 0.16342412
A5: Итого | B5: =SUM(B2:B4) -> 1.8333333 | C5: =SUM(C2:C4) -> 3.5 | D5: =SUM(D2:D4) -> 6 | E5: =SUM(E2:E4) -> 3.3674418 | F5: =SUM(F2:F4) -> 1
A6: L_max | B6: =B5*F2+C5*F3+D5*F4 -> 3.0092027
A7: ИС | B7: =(B6-'2Данные'!D20)/('2Данные'!D20 - 1) -> 0.0046013564
A8: ОС | B8: =B7/'2Данные'!D21 -> 0.007933373

Sheet 2Итог
B1: К1 | C1: К2 | D1: К3 | G1: К4 | H1: Итоговая оценка коэф.
B2: {=TRANSPOSE('2Критерии'!G2:G7)} -> 2 | C2: 3 | D2: 2 | E2: 0.5 | F2: 4 | G2: 1
A3: My | B3: {='2K1'!F2:F4} -> 0.16342412 | C3: {='2K2'!F2:F4} -> 0.14285714 | D3: {='2K3'!F2:F4} -> 0.25 | E3: {='2K4'!F2:F4} -> 0.45454545 | F3: {='2K5'!F2:F4} -> 0.47368421 | G3: {='2K6'!F2:F4} -> 0.53961455 | H3: =B$2*B3+C$2*C3+D$2*D3+E$2*E3+F$2*F3+G$2*G3 -> 3.9170438
A4: Postgres | B4: 0.29696133 | C4: 0.42857143 | D4: 0.25 | E4: 0.45454545 | F4: 0.47368421 | G4: 0.29696133 | H4: =B$2*B4+C$2*C4+D$2*D4+E$2*E4+F$2*F4+G$2*G4 -> 4.7986078 | I4: Наиболее предпочтительный
A5: MS | B5: 0.53961455 | C5: 0.42857143 | D5: 0.5 | E5: 0.090909091 | F5: 0.052631579 | G5: 0.16342412 | H5: =B$2*B5+C$2*C5+D$2*D5+E$2*E5+F$2*F5+G$2*G5 -> 3.7843484 | I5: Наименее предпочтительный
A6: ИС | B6: ='2K1'!B7 -> 0.0046013564 | C6: ='2K2'!B7 -> 0 | D6: ='2K3'!B7 -> 2.220446e-16 | E6: ='2K4'!B7 -> 0 | F6: ='2K5'!B7 -> 0 | G6: ='2K6'!B7 -> 0.0046013564
A7: ОИС | B7: =B2*B6+C2*C6+D2*D6+G2*G6 -> 0.013804069
A8: ООС | B8: =B7/Данные!D19 -> 0.023800119
